cupid/__init__.py
cupid-0.0.0.dist-info/METADATA
cupid-0.0.0.dist-info/WHEEL
cupid-0.0.0.dist-info/top_level.txt
cupid-0.0.0.dist-info/RECORD
